phenomate_core/__init__.py
phenomate_core/get_version.py
phenomate_core/preprocessing/__init__.py
phenomate_core/preprocessing/base.py
phenomate_core/preprocessing/canbus/__init__.py
phenomate_core/preprocessing/canbus/process.py
phenomate_core/preprocessing/hyperspec/__init__.py
phenomate_core/preprocessing/hyperspec/hyperspec.proto
phenomate_core/preprocessing/hyperspec/hyperspec_pb2.py
phenomate_core/preprocessing/hyperspec/hyperspec_pb2.pyi
phenomate_core/preprocessing/hyperspec/process.py
phenomate_core/preprocessing/imu/__init__.py
phenomate_core/preprocessing/imu/process.py
phenomate_core/preprocessing/jai/__init__.py
phenomate_core/preprocessing/jai/jai.proto
phenomate_core/preprocessing/jai/jai_pb2.py
phenomate_core/preprocessing/jai/jai_pb2.pyi
phenomate_core/preprocessing/jai/process.py
phenomate_core/preprocessing/lidar2d/__init__.py
phenomate_core/preprocessing/lidar2d/lidar.proto
phenomate_core/preprocessing/lidar2d/lidar_pb2.py
phenomate_core/preprocessing/lidar2d/lidar_pb2.pyi
phenomate_core/preprocessing/lidar2d/process.py
phenomate_core/preprocessing/lidar2d/reading_proto_buff.py
phenomate_core/preprocessing/lidar2d/sick_scan_api.py
phenomate_core/preprocessing/lidar3douster/__init__.py
phenomate_core/preprocessing/lidar3douster/process.py
phenomate_core/preprocessing/oak_d/__init__.py
phenomate_core/preprocessing/oak_d/oak.proto
phenomate_core/preprocessing/oak_d/oak_pb2.py
phenomate_core/preprocessing/oak_d/oak_pb2.pyi
phenomate_core/preprocessing/oak_d/process.py
phenomate_core/preprocessing/rs3basestation/__init__.py
phenomate_core/preprocessing/rs3basestation/process.py
phenomate_core/py.typed
phenomate_core-0.4.0.dist-info/WHEEL
phenomate_core-0.4.0.dist-info/METADATA
phenomate_core-0.4.0.dist-info/RECORD
