Metadata-Version: 2.3
Name: phenomate-core
Version: 0.4.0
Summary: Add your description here
Requires-Dist: google>=3.0.0
Requires-Dist: numpy>=2.3.1
Requires-Dist: opencv-python>=4.11.0.86
Requires-Dist: pillow>=11.3.0
Requires-Dist: protobuf>=6.31.1
Requires-Dist: pyturbojpeg
Requires-Dist: spectral>=0.24
Requires-Dist: tifffile[all]>=2025.9.30
Requires-Python: >=3.11
